scim2_server/__init__.py
scim2_server/backend.py
scim2_server/cli.py
scim2_server/filter.py
scim2_server/operators.py
scim2_server/provider.py
scim2_server/resources/default-resource-types.json
scim2_server/resources/default-schemas.json
scim2_server/utils.py
scim2_server-0.1.8.dist-info/WHEEL
scim2_server-0.1.8.dist-info/entry_points.txt
scim2_server-0.1.8.dist-info/METADATA
scim2_server-0.1.8.dist-info/RECORD
