Metadata-Version: 2.3
Name: scim2-server
Version: 0.1.8
Summary: Lightweight SCIM2 server prototype
Keywords: scim,scim2,provisioning,rfc7643,rfc7644
Author: Yaal Coop, Christian Friedrich Coors
Author-email: Yaal Coop <contact@yaal.coop>, Christian Friedrich Coors <me@ccoors.de>
License:                                  Apache License
Classifier: Intended Audience :: Developers
Classifier: Development Status :: 4 - Beta
Classifier: Programming Language :: Python :: 3.10
Classifier: Programming Language :: Python :: 3.11
Classifier: Programming Language :: Python :: 3.12
Classifier: Programming Language :: Python :: 3.13
Classifier: Programming Language :: Python :: 3.14
Classifier: Programming Language :: Python :: Implementation :: CPython
Classifier: License :: OSI Approved :: Apache Software License
Classifier: Environment :: Web Environment
Classifier: Programming Language :: Python
Classifier: Operating System :: OS Independent
Requires-Dist: scim2-filter-parser>=0.7.0
Requires-Dist: scim2-models>=0.6.1
Requires-Dist: werkzeug>=3.0.3
Requires-Python: >=3.10
Project-URL: funding, https://github.com/sponsors/python-scim
Project-URL: repository, https://github.com/python-scim/scim2-server
